_postgresql.pypy38-pp73-x86_64-linux-gnu.so
_postgresql.abi3.so
postgresql_wheel-14.1.2.dist-info/METADATA
postgresql_wheel-14.1.2.dist-info/WHEEL
postgresql_wheel-14.1.2.dist-info/RECORD
postgresql_wheel-14.1.2.dist-info/LICENSE
postgresql_wheel-14.1.2.dist-info/top_level.txt
postgresql/__init__.py
postgresql/build.py
postgresql/_version.py
postgresql/tests/test_postgresql.py
postgresql/tests/__init__.py
