Metadata-Version: 2.1
Name: postgresql-wheel
Version: 14.1.2
Summary: PostgreSQL Server compiled into a Python Wheel.
Home-page: https://github.com/michelp/postgresql-wheel
Author: Michel Pelletier
License: Apache License 2.0
Keywords: graphblas,graph,sparse,matrix,suitesparse,hypersparse,hypergraph
Platform: UNKNOWN
Classifier: Development Status :: 4 - Beta
Classifier: License :: OSI Approved :: Apache Software License
Classifier: Operating System :: MacOS :: MacOS X
Classifier: Operating System :: POSIX :: Linux
Classifier: Operating System :: Microsoft :: Windows
Classifier: Programming Language :: Python
Classifier: Programming Language :: Python :: 3
Classifier: Programming Language :: Python :: 3.7
Classifier: Programming Language :: Python :: 3.8
Classifier: Programming Language :: Python :: 3.9
Classifier: Programming Language :: Python :: 3 :: Only
Classifier: Intended Audience :: Developers
Classifier: Intended Audience :: Science/Research
Classifier: Topic :: Scientific/Engineering
Classifier: Topic :: Scientific/Engineering :: Mathematics
Requires-Python: >=3.7,<3.10
License-File: LICENSE
Requires-Dist: pytest
